{"cameraMode":{"drawMode":0,"name":"Shaded","section":"Shading Mode"},"sceneLighting":true,"audioPlay":false,"sceneViewState":{"m_AlwaysRefresh":false,"showFog":true,"showSkybox":true,"showFlares":true,"showImageEffects":true,"showParticleSystems":true,"showVisualEffectGraphs":true,"m_FxEnabled":true},"in2DMode":false,"pivot":{"x":-0.23629489541053773,"y":25.903972625732423,"z":0.700510561466217},"rotation":{"x":0.563865065574646,"y":-0.02600451372563839,"z":0.017767583951354028,"w":0.8252661824226379},"size":1.9352562427520753,"orthographic":false}